simplenlg/__init__.py
simplenlg/features/ClauseStatus.py
simplenlg/features/DiscourseFunction.py
simplenlg/features/Feature.py
simplenlg/features/Form.py
simplenlg/features/Gender.py
simplenlg/features/Inflection.py
simplenlg/features/InternalFeature.py
simplenlg/features/InterrogativeType.py
simplenlg/features/LexicalFeature.py
simplenlg/features/NumberAgreement.py
simplenlg/features/Person.py
simplenlg/features/Tense.py
simplenlg/features/__init__.py
simplenlg/format/__init__.py
simplenlg/format/english/NumberedPrefix.py
simplenlg/format/english/TextFormatter.py
simplenlg/format/english/__init__.py
simplenlg/framework/CoordinatedPhraseElement.py
simplenlg/framework/DocumentCategory.py
simplenlg/framework/DocumentElement.py
simplenlg/framework/InflectedWordElement.py
simplenlg/framework/LexicalCategory.py
simplenlg/framework/ListElement.py
simplenlg/framework/NLGElement.py
simplenlg/framework/NLGFactory.py
simplenlg/framework/NLGModule.py
simplenlg/framework/PhraseCategory.py
simplenlg/framework/PhraseElement.py
simplenlg/framework/StringElement.py
simplenlg/framework/WordElement.py
simplenlg/framework/__init__.py
simplenlg/lexicon/Lexicon.py
simplenlg/lexicon/XMLLexicon.py
simplenlg/lexicon/__init__.py
simplenlg/morphology/__init__.py
simplenlg/morphology/english/DeterminerAgrHelper.py
simplenlg/morphology/english/MorphologyProcessor.py
simplenlg/morphology/english/MorphologyRules.py
simplenlg/morphology/english/__init__.py
simplenlg/orthography/__init__.py
simplenlg/orthography/english/OrthographyProcessor.py
simplenlg/orthography/english/__init__.py
simplenlg/phrasespec/AdjPhraseSpec.py
simplenlg/phrasespec/AdvPhraseSpec.py
simplenlg/phrasespec/NPPhraseSpec.py
simplenlg/phrasespec/PPPhraseSpec.py
simplenlg/phrasespec/SPhraseSpec.py
simplenlg/phrasespec/VPPhraseSpec.py
simplenlg/phrasespec/__init__.py
simplenlg/realiser/__init__.py
simplenlg/realiser/english/Realiser.py
simplenlg/realiser/english/__init__.py
simplenlg/resources/__init__.py
simplenlg-0.2.0.dist-info/LICENSE.md
simplenlg-0.2.0.dist-info/METADATA
simplenlg-0.2.0.dist-info/WHEEL
simplenlg-0.2.0.dist-info/top_level.txt
simplenlg-0.2.0.dist-info/RECORD
