Metadata-Version: 2.1
Name: simplenlg
Version: 0.2.0
Summary: Python Implementation of SimpleNLG
Home-page: https://github.com/bjascob/pySimpleNLG
Author: Brad Jascob
Author-email: bjascob@msn.com
License: UNKNOWN
Platform: UNKNOWN
Classifier: Programming Language :: Python :: 3
Classifier: License :: OSI Approved :: Mozilla Public License 1.1 (MPL 1.1)
Classifier: Operating System :: OS Independent
